Design.v
`timescale 1ns / 1ps
//////////////////////////////////////////////////////////////////////////////////
// Company: 
// Engineer: 
// 
// Create Date: 17.04.2026 15:23:54
// Design Name: 
// Module Name: BtGconvertor
// Project Name: 
// Target Devices: 
// Tool Versions: 
// Description: 
// 
// Dependencies: 
// 
// Revision:
// Revision 0.01 - File Created
// Additional Comments:
// 
//////////////////////////////////////////////////////////////////////////////////


module BtGconvertor(
   input [3:0]a_i,
   output [3:0]b_o 
);

//Behavioural Representation
//assign b_o = a_i ^ (a_i >> 1); //behavioural modelling
assign b_o[3] = a_i[3]; //dataflow modelling
assign b_o[2] = a_i[2] ^ a_i[3];
assign b_o[1] = a_i[1] ^ a_i[2];
assign b_o[0] = a_i[0] ^ a_i[1];

endmodule

Testbench.v
`timescale 1ns / 1ps
//////////////////////////////////////////////////////////////////////////////////
// Company: 
// Engineer: 
// 
// Create Date: 17.04.2026 15:24:36
// Design Name: 
// Module Name: tb_BtGconvertor
// Project Name: 
// Target Devices: 
// Tool Versions: 
// Description: 
// 
// Dependencies: 
// 
// Revision:
// Revision 0.01 - File Created
// Additional Comments:
// 
//////////////////////////////////////////////////////////////////////////////////


module tb_BtGconvertor();
reg [3:0]a_ti;
wire [3:0]b_to;

//net(s)
integer i;
reg [3:0]exp_gray;
integer count;
integer pass;
integer fail;

//instantiation
BtGconvertor DUT(.a_i(a_ti), 
   .b_o(b_to));

//input feeding
initial begin
a_ti = 4'b0000;
#2;
check();
for(i = 1; i < 16; i = i + 1) begin //loop feed
   #3 a_ti = i;
   #2;
   check();
end
$display("-----------"); //status display
$display("Total Checks: %d | Pass: %d, Fail: %d", count, pass, fail);
$display("-----------");
#5 $finish;
end

//self checker
task check(); begin
exp_gray[3] = a_ti[3];
exp_gray[2] = a_ti[2] ^ a_ti[3];
exp_gray[1] = a_ti[1] ^ a_ti[2];
exp_gray[0] = a_ti[0] ^ a_ti[1];
if(exp_gray !== b_to) begin
   fail = fail + 1;
   $display("Time: %0t | Binary: %b, Gray: %b | Expected Gray: %b", $time, a_ti, b_to, exp_gray);
   //$fatal(1, "Time: %0t | Binary: %b, Gray: %b | Expected Gray: %b", $time, a_ti, b_to, exp_gray); 
   //fatal error tag: 0-stop(default), 1(current time step), 2(current simulation time)
end
else 
   pass = pass + 1;
count = count + 1;
end
endtask

//initialization
initial begin 
count = 0;
pass = 0;
fail = 0;
end

//capture
initial begin
$monitor("Time: %0t | Binary: %b, Gray: %b", $time, a_ti, b_to);
$dumpfile("BtG_Convertor.vcd");
$dumpvars(0, tb_BtGconvertor);
end

endmodule

BtG_Convertor.vcd
$date
   Fri Apr 17 15:50:45 2026
$end

$version
  2025.2
  $dumpfile ("BtG_Convertor.vcd") 
$end

$timescale
  1ps
$end

$scope module tb_BtGconvertor $end
$var reg 4 ! a_ti [3:0] $end
$var wire 4 " b_to [3:0] $end
$var integer 32 # i [31:0] $end
$var reg 4 $ exp_gray [3:0] $end
$var integer 32 % count [31:0] $end
$var integer 32 & pass [31:0] $end
$var integer 32 ' fail [31:0] $end
$scope module DUT $end
$var wire 4 ( a_i [3:0] $end
$var wire 4 " b_o [3:0] $end
$upscope $end
$scope task check $end
$upscope $end
$upscope $end
$enddefinitions $end

#0
$dumpvars
b0 !
b0 "
bx #
bx $
b0 %
b0 &
b0 '
b0 (
$end

#2000
b1 #
b0 $
b1 %
b1 &

#5000
b1 !
b1 "
b1 (

#7000
b10 #
b1 $
b10 %
b10 &

#10000
b10 !
b11 "
b10 (

#12000
b11 #
b11 $
b11 %
b11 &

#15000
b11 !
b10 "
b11 (

#17000
b100 #
b10 $
b100 %
b100 &

#20000
b100 !
b110 "
b100 (

#22000
b101 #
b110 $
b101 %
b101 &

#25000
b101 !
b111 "
b101 (

#27000
b110 #
b111 $
b110 %
b110 &

#30000
b110 !
b101 "
b110 (

#32000
b111 #
b101 $
b111 %
b111 &

#35000
b111 !
b100 "
b111 (

#37000
b1000 #
b100 $
b1000 %
b1000 &

#40000
b1000 !
b1100 "
b1000 (

#42000
b1001 #
b1100 $
b1001 %
b1001 &

#45000
b1001 !
b1101 "
b1001 (

#47000
b1010 #
b1101 $
b1010 %
b1010 &

#50000
b1010 !
b1111 "
b1010 (

#52000
b1011 #
b1111 $
b1011 %
b1011 &

#55000
b1011 !
b1110 "
b1011 (

#57000
b1100 #
b1110 $
b1100 %
b1100 &

#60000
b1100 !
b1010 "
b1100 (

#62000
b1101 #
b1010 $
b1101 %
b1101 &

#65000
b1101 !
b1011 "
b1101 (

#67000
b1110 #
b1011 $
b1110 %
b1110 &

#70000
b1110 !
b1001 "
b1110 (

#72000
b1111 #
b1001 $
b1111 %
b1111 &

#75000
b1111 !
b1000 "
b1111 (

#77000
b10000 #
b1000 $
b10000 %
b10000 &
